csp_observer/__init__.py
csp_observer/admin.py
csp_observer/apps.py
csp_observer/managers.py
csp_observer/middleware.py
csp_observer/models.py
csp_observer/remote.py
csp_observer/report_handlers.py
csp_observer/rule_evaluator.py
csp_observer/settings.py
csp_observer/tests.py
csp_observer/update.py
csp_observer/urls.py
csp_observer/views.py
csp_observer/migrations/0001_initial.py
csp_observer/migrations/0002_auto_20200618_1232.py
csp_observer/migrations/0003_auto_20200703_1300.py
csp_observer/migrations/0004_csprule_is_custom_rule.py
csp_observer/migrations/0005_auto_20200819_1908.py
csp_observer/migrations/0006_auto_20200819_1920.py
csp_observer/migrations/0007_config.py
csp_observer/migrations/0008_auto_20200819_1955.py
csp_observer/migrations/0009_auto_20200821_0838.py
csp_observer/migrations/0010_auto_20200822_1446.py
csp_observer/migrations/0011_auto_20200822_1531.py
csp_observer/migrations/__init__.py
csp_observer/static/csp_observer/css/Chart.min.css
csp_observer/static/csp_observer/css/base.css
csp_observer/static/csp_observer/css/bootstrap.min.css
csp_observer/static/csp_observer/css/clientui.css
csp_observer/static/csp_observer/img/alert-circle.svg
csp_observer/static/csp_observer/img/check-circle.svg
csp_observer/static/csp_observer/img/cspo-logo-256px.png
csp_observer/static/csp_observer/img/cspo-logo-64px.png
csp_observer/static/csp_observer/img/cspo-logo.png
csp_observer/static/csp_observer/js/Chart.min.js
csp_observer/static/csp_observer/js/base.js
csp_observer/static/csp_observer/js/bootstrap.min.js
csp_observer/static/csp_observer/js/chartjs-plugin-colorschemes.min.js
csp_observer/static/csp_observer/js/clientui.js
csp_observer/static/csp_observer/js/ignoreButton.js
csp_observer/static/csp_observer/js/jquery.min.js
csp_observer/static/csp_observer/js/tripwire.js
csp_observer/templates/cspo_base.html
csp_observer/templates/admin/dashboard.html
csp_observer/templates/client_ui/popup.html
csp_observer/templates/client_ui/privacy.html
django_csp_observer-1.0.2.dist-info/LICENSE
django_csp_observer-1.0.2.dist-info/METADATA
django_csp_observer-1.0.2.dist-info/WHEEL
django_csp_observer-1.0.2.dist-info/top_level.txt
django_csp_observer-1.0.2.dist-info/RECORD
